programgarden_dashboard/__init__.py
programgarden_dashboard/components/__init__.py
programgarden_dashboard/components/account.py
programgarden_dashboard/components/order_book.py
programgarden_dashboard/components/order_panel.py
programgarden_dashboard/components/stock_card.py
programgarden_dashboard/components/trading_view_chart.py
programgarden_dashboard/components/watchlist.py
programgarden_dashboard/dashboard.py
programgarden_dashboard/data/__init__.py
programgarden_dashboard/data/ls/__init__.py
programgarden_dashboard/data/ls/ls_provider.py
programgarden_dashboard/data/ls/ls_tr.py
programgarden_dashboard/data/ls/ls_websocket.py
programgarden_dashboard/data/provider.py
programgarden_dashboard/data/yahoo/__init__.py
programgarden_dashboard/data/yahoo/yahoo_provider.py
programgarden_dashboard/data/yahoo/yahoo_tr.py
programgarden_dashboard/data/yahoo/yahoo_websocket.py
programgarden_dashboard/pages/__init__.py
programgarden_dashboard/pages/error.py
programgarden_dashboard/pages/user_guide.py
programgarden_dashboard/ui/__init__.py
programgarden_dashboard/ui/grid_layout.py
programgarden_dashboard/utils/__init__.py
programgarden_dashboard/utils/data_formatter.py
programgarden_dashboard/utils/logger.py
programgarden_dashboard/utils/proxies.py
programgarden_dashboard-0.1.2.dist-info/LICENSE
programgarden_dashboard-0.1.2.dist-info/METADATA
programgarden_dashboard-0.1.2.dist-info/WHEEL
programgarden_dashboard-0.1.2.dist-info/RECORD
