Metadata-Version: 2.3
Name: programgarden-dashboard
Version: 0.1.2
Summary: LS Open API를 기반으로 사용할 수 있는 간단한 웹 대시보드 라이브러리
License: AGPL-3.0-or-later
Keywords: LS증권,finance,trading,WTS,dashboard
Author: 전현우
Author-email: rakunary@programgarden.com
Requires-Python: >=3.9
Classifier: License :: OSI Approved :: GNU Affero General Public License v3 or later (AGPLv3+)
Classifier: Programming Language :: Python :: 3
Classifier: Programming Language :: Python :: 3.9
Classifier: Programming Language :: Python :: 3.10
Classifier: Programming Language :: Python :: 3.11
Classifier: Programming Language :: Python :: 3.12
Classifier: Programming Language :: Python :: 3.13
Requires-Dist: nicegui (>=2.24.2)
Requires-Dist: programgarden-finance (>=0.1.2)
Requires-Dist: yfinance (>=0.2.66)
Project-URL: Homepage, https://programgarden.com
